tbse/__main__.py
tbse/setup_guide.py
tbse/tb.py
tbse/tbse.py
tbse/dat/tool.py
tbse/dat/libs/clearqq.py
tbse/dat/libs/dol.py
tbse/dat/libs/txts.py
tbse-3.3.99.2.data/scripts/tb.py
tbse-3.3.99.2.data/scripts/tbse.py
tbse-3.3.99.2.dist-info/METADATA
tbse-3.3.99.2.dist-info/WHEEL
tbse-3.3.99.2.dist-info/top_level.txt
tbse-3.3.99.2.dist-info/RECORD
